[
    {
        "restaurantid": 4,
        "restaurant": "Cinderella's Royal Table"
    },
    {
        "restaurantid": 5,
        "restaurant": "Aloha Isle"
    },
    {
        "restaurantid": 6,
        "restaurant": "Aunt Polly's"
    },
    {
        "restaurantid": 7,
        "restaurant": "Auntie Gravity's Galactic Goodies"
    },
    {
        "restaurantid": 8,
        "restaurant": "Be Our Guest Restaurant"
    },
    {
        "restaurantid": 9,
        "restaurant": "Casey's Corner"
    },
    {
        "restaurantid": 10,
        "restaurant": "Cheshire Cafe"
    },
    {
        "restaurantid": 11,
        "restaurant": "Columbia Harbour House"
    },
    {
        "restaurantid": 12,
        "restaurant": "Cool Ship"
    },
    {
        "restaurantid": 13,
        "restaurant": "Cosmic Ray's Starlight Cafe"
    },
    {
        "restaurantid": 14,
        "restaurant": "Gaston's Tavern"
    },
    {
        "restaurantid": 15,
        "restaurant": "Golden Oak Outpost"
    },
    {
        "restaurantid": 16,
        "restaurant": "Jungle Navigation Co. Ltd. Skipper Canteen"
    },
    {
        "restaurantid": 17,
        "restaurant": "Liberty Square Market"
    },
    {
        "restaurantid": 18,
        "restaurant": "Liberty Tree Tavern"
    },
    {
        "restaurantid": 19,
        "restaurant": "Main Street Bakery"
    },
    {
        "restaurantid": 20,
        "restaurant": "Pecos Bill Tall Tale Inn and Cafe"
    },
    {
        "restaurantid": 21,
        "restaurant": "Pinocchio Village Haus"
    },
    {
        "restaurantid": 22,
        "restaurant": "Plaza Ice Cream Parlor"
    },
    {
        "restaurantid": 23,
        "restaurant": "Prince Eric's Village Market"
    },
    {
        "restaurantid": 24,
        "restaurant": "Sleepy Hollow"
    },
    {
        "restaurantid": 25,
        "restaurant": "Storybook Treats"
    },
    {
        "restaurantid": 26,
        "restaurant": "Sunshine Tree Terrace"
    },
    {
        "restaurantid": 27,
        "restaurant": "The Crystal Palace"
    },
    {
        "restaurantid": 28,
        "restaurant": "The Diamond Horseshoe"
    },
    {
        "restaurantid": 29,
        "restaurant": "The Friar's Nook"
    },
    {
        "restaurantid": 30,
        "restaurant": "The Lunching Pad"
    },
    {
        "restaurantid": 31,
        "restaurant": "The Plaza Restaurant"
    },
    {
        "restaurantid": 32,
        "restaurant": "Tomorrowland Terrace Restaurant"
    },
    {
        "restaurantid": 33,
        "restaurant": "Tony's Town Square Restaurant"
    },
    {
        "restaurantid": 34,
        "restaurant": "Tortuga Tavern"
    },
    {
        "restaurantid": 35,
        "restaurant": "Westward Ho"
    }
]
